grizzly/__init__.py
grizzly/__main__.py
grizzly/args.py
grizzly/conftest.py
grizzly/main.py
grizzly/py.typed
grizzly/session.py
grizzly/test_args.py
grizzly/test_main.py
grizzly/test_session.py
grizzly/adapter/__init__.py
grizzly/adapter/adapter.py
grizzly/adapter/test_adapter.py
grizzly/adapter/no_op_adapter/__init__.py
grizzly/adapter/no_op_adapter/test_no_op.py
grizzly/common/__init__.py
grizzly/common/bugzilla.py
grizzly/common/cache.py
grizzly/common/frontend.py
grizzly/common/fuzzmanager.py
grizzly/common/harness.html
grizzly/common/iomanager.py
grizzly/common/plugins.py
grizzly/common/post_launch_delay.html
grizzly/common/report.py
grizzly/common/reporter.py
grizzly/common/runner.py
grizzly/common/stack_hasher.py
grizzly/common/status.py
grizzly/common/status_reporter.py
grizzly/common/storage.py
grizzly/common/test_bugzilla.py
grizzly/common/test_cache.py
grizzly/common/test_frontend.py
grizzly/common/test_fuzzmanager.py
grizzly/common/test_iomanager.py
grizzly/common/test_plugins.py
grizzly/common/test_report.py
grizzly/common/test_reporter.py
grizzly/common/test_runner.py
grizzly/common/test_stack_hasher.py
grizzly/common/test_status.py
grizzly/common/test_status_reporter.py
grizzly/common/test_storage.py
grizzly/common/test_utils.py
grizzly/common/utils.py
grizzly/reduce/__init__.py
grizzly/reduce/__main__.py
grizzly/reduce/args.py
grizzly/reduce/bucket.py
grizzly/reduce/conftest.py
grizzly/reduce/core.py
grizzly/reduce/crash.py
grizzly/reduce/exceptions.py
grizzly/reduce/main.py
grizzly/reduce/test_main.py
grizzly/reduce/test_main_fm.py
grizzly/reduce/test_reduce.py
grizzly/reduce/test_strategies.py
grizzly/reduce/test_strategies_beautifulsoup.py
grizzly/reduce/test_strategies_beautify.py
grizzly/reduce/strategies/__init__.py
grizzly/reduce/strategies/beautifulsoup.py
grizzly/reduce/strategies/beautify.py
grizzly/reduce/strategies/lithium.py
grizzly/reduce/strategies/testcases.py
grizzly/replay/__init__.py
grizzly/replay/__main__.py
grizzly_framework-0.24.2.dist-info/licenses/LICENSE
grizzly_framework-0.24.2.dist-info/METADATA
grizzly_framework-0.24.2.dist-info/WHEEL
grizzly_framework-0.24.2.dist-info/entry_points.txt
grizzly_framework-0.24.2.dist-info/top_level.txt
grizzly_framework-0.24.2.dist-info/RECORD
