Metadata-Version: 2.4
Name: grizzly-framework
Version: 0.24.2
Summary: A framework for developing and running browser fuzzers
Home-page: https://github.com/MozillaSecurity/grizzly
Author: Tyson Smith
Author-email: twsmith@mozilla.com
Maintainer: Mozilla Fuzzing Team
Maintainer-email: fuzzing@mozilla.com
License: MPL 2.0
Keywords: firefox framework fuzz fuzzing test testing
Classifier: Intended Audience :: Developers
Classifier: License :: OSI Approved :: Mozilla Public License 2.0 (MPL 2.0)
Classifier: Programming Language :: Python :: 3
Classifier: Topic :: Security
Classifier: Topic :: Software Development :: Testing
Requires-Python: >=3.9
License-File: LICENSE
Requires-Dist: aioquic==1.2.0
Requires-Dist: beautifulsoup4
Requires-Dist: bugsy
Requires-Dist: cryptography
Requires-Dist: cssbeautifier
Requires-Dist: fasteners
Requires-Dist: ffpuppet>=0.17.0
Requires-Dist: fxpoppet>=0.4.0
Requires-Dist: FuzzManager
Requires-Dist: jsbeautifier
Requires-Dist: lithium-reducer>=3.0.0
Requires-Dist: prefpicker>=1.23.0
Requires-Dist: psutil>=5.9.4
Provides-Extra: dev
Requires-Dist: pre-commit; extra == "dev"
Requires-Dist: tox; extra == "dev"
Dynamic: license-file
